djangopebble/.gitignore
djangopebble/README.en.md
djangopebble/README.md
djangopebble/__init__.py
djangopebble/create_user.py
djangopebble/exec.py
djangopebble/html2txt.py
djangopebble/markdown2txt.py
djangopebble/pure.py
djangopebble/re_symbol.py
djangopebble/.git/HEAD
djangopebble/.git/config
djangopebble/.git/description
djangopebble/.git/index
djangopebble/.git/packed-refs
djangopebble/.git/hooks/applypatch-msg.sample
djangopebble/.git/hooks/commit-msg.sample
djangopebble/.git/hooks/fsmonitor-watchman.sample
djangopebble/.git/hooks/post-update.sample
djangopebble/.git/hooks/pre-applypatch.sample
djangopebble/.git/hooks/pre-commit.sample
djangopebble/.git/hooks/pre-merge-commit.sample
djangopebble/.git/hooks/pre-push.sample
djangopebble/.git/hooks/pre-rebase.sample
djangopebble/.git/hooks/pre-receive.sample
djangopebble/.git/hooks/prepare-commit-msg.sample
djangopebble/.git/hooks/update.sample
djangopebble/.git/info/exclude
djangopebble/.git/logs/HEAD
djangopebble/.git/logs/refs/heads/master
djangopebble/.git/logs/refs/remotes/origin/HEAD
djangopebble/.git/objects/pack/pack-7ba958878273b437e7cad9424be1891d21d64233.idx
djangopebble/.git/objects/pack/pack-7ba958878273b437e7cad9424be1891d21d64233.pack
djangopebble/.git/refs/heads/master
djangopebble/.git/refs/remotes/origin/HEAD
djangopebble/.gitee/ISSUE_TEMPLATE.zh-CN.md
djangopebble/.gitee/PULL_REQUEST_TEMPLATE.zh-CN.md
djangopebble/adminclass/__init__.py
djangopebble/adminclass/admin_env_init.py
djangopebble/adminclass/adminclass.py
djangopebble/django/__init__.py
djangopebble/django/auth.py
djangopebble/django/conf.py
djangopebble/django/mixins.py
djangopebble/django/utils.py
djangopebble/django/views.py
djangopebble/djangopebble/create_user.py
djangopebble/djangopebble/exec.py
djangopebble/djangopebble/html2txt.py
djangopebble/djangopebble/markdown2txt.py
djangopebble/djangopebble/pure.py
djangopebble/djangopebble/re_symbol.py
djangopebble/djangopebble/adminclass/__init__.py
djangopebble-0.0.1.dist-info/METADATA
djangopebble-0.0.1.dist-info/WHEEL
djangopebble-0.0.1.dist-info/top_level.txt
djangopebble-0.0.1.dist-info/RECORD
