Metadata-Version: 2.1
Name: djangopebble
Version: 0.0.1
Summary: Wish this package be your pebble in using Django.
Home-page: https://gitee.com/hedong-guest/djangopebble
Author: jml
Author-email: 642201822@qq.com
License: UNKNOWN
Platform: UNKNOWN
Classifier: Programming Language :: Python :: 3
Classifier: License :: OSI Approved :: MIT License
Classifier: Operating System :: OS Independent
Requires-Python: >=3.6
Requires-Dist: pandas
Requires-Dist: django
Requires-Dist: openpyxl
Requires-Dist: xlrd (==1.2.0)
Requires-Dist: bdtime
Requires-Dist: tqdm
